{"p814QZo9pxszXekCzQXL3g==":"susan-yin-2jivbogleho-unsplash-2000x1335.jpg","DQw85/3vCF01ptZ+PUSiaA==":"lady1-676x451.jpg","TGejxFJw1SqQhOMY9kWoJQ==":"book1-676x451.jpg","aArhehgFM5poROAWRX8ezQ==":"lady2-676x448.jpg","+2df6MgGkqnEok5JzonolQ==":"logo2.png","/5TxP6rB5Xsj6wML99MSww==":"logo2-1.png","pa5Dkwo/T1qgW/t0h+fQvA==":"background5.jpg","+Cn0OWPPPGVib77X+PQagQ==":"book2-102x102.jpg","hTrjrr2bZHudsC9xv0kcoQ==":"susan-yin-2jivbogleho-unsplash-436x291.jpg","64ZvcZEVjNmPGWWah66OuA==":"schholpic1-640x426.jpg","RnIzEwXLFXWcbfJ6N7qjhA==":"scholpic3-436x327.jpg","EOMA18LLE1w0+CZJ4QzOjQ==":"unity-420x420.jpg","ikqHbsRoGx11T/NEyqVKCA==":"ethiopian-flag-3-96x75.png","ZX+hsyafb9NZ2VrZTTSw+Q==":"book2-2000x2000.jpg","/QEm6eCtKme8b3dF7ii21Q==":"ethiopia-boys-reading-in-library-600x339.jpg","9YuMj87+8zzGfR707wAF7Q==":"img-3975-676x507.jpg","3AI2t5sBOQecPk5Iqzj53Q==":"ethiopia-boys-reading-in-library-600x339.jpeg","7Cik7isLgw9lLUW0/HKrFQ==":"img-3975-676x507.jpeg","Vn7NnG4z6t32R1sd1OmL3w==":"img-3976-676x507.jpeg","qq7LbgUe6u3WtVcMt4lhmw==":"ethiopian-flag-898x504.jpg","LNhBLhybtrvUxAg835yuUg==":"schoolpic2-1980x1043.jpg","4Gz90uwRyzxgCQ+Qu9e0mw==":"together2-474x440.jpg","OlFiuHZVQJmhndLsKe0hng==":"together1-1300x957.jpg","BRvaeIiFXEB89VtblCsfTA==":"5-192x192.png","d+IOrYGCYqJXsg6sV59q0g==":"5-1-192x192.png"}